http_pycurl/__init__.py
http_pycurl/api.py
http_pycurl/exceptions.py
http_pycurl/models.py
http_pycurl/sessions.py
http_pycurl/structures.py
http_pycurl/utils.py
tests/__init__.py
tests/test_http.py
http_pycurl-1.0.2.dist-info/LICENSE
http_pycurl-1.0.2.dist-info/METADATA
http_pycurl-1.0.2.dist-info/WHEEL
http_pycurl-1.0.2.dist-info/top_level.txt
http_pycurl-1.0.2.dist-info/RECORD
