Metadata-Version: 2.1
Name: http-pycurl
Version: 1.0.2
Summary: http_pycurl rewraps pycurl.
Home-page: https://github.com/pythonqi/http_pycurl
Author: pythonqi
Author-email: pythonqi@outlook.com
License: UNKNOWN
Platform: UNKNOWN
Classifier: Programming Language :: Python :: 3
Classifier: License :: OSI Approved :: MIT License
Classifier: Operating System :: OS Independent
Requires-Python: >=3.4
Requires-Dist: pycurl
